dataFilterTool/__init__.py
dataFilterTool/avg_sal_des.py
dataFilterTool/config.py
dataFilterTool/join_date_filter.py
dataFilterTool/main.py
dataFilterTool-0.0.9.dist-info/METADATA
dataFilterTool-0.0.9.dist-info/WHEEL
dataFilterTool-0.0.9.dist-info/top_level.txt
dataFilterTool-0.0.9.dist-info/RECORD
