Metadata-Version: 2.1
Name: dataFilterTool
Version: 0.0.9
Summary: DataFilterTool is a Python package designed to 
Author: Lavanya
Author-email: lavanya.narang@dataverze.ai
Classifier: Programming Language :: Python :: 3
Classifier: License :: OSI Approved :: MIT License
Classifier: Operating System :: OS Independent
Requires-Python: >=3.7
Requires-Dist: pytest
Requires-Dist: pylance
Requires-Dist: black
Requires-Dist: pandas
Requires-Dist: xlsxwriter
Requires-Dist: openpyxl
